{
  "type": "object",
  "properties": {
    "ztysj1mzc30": {
      "type": "void",
      "x-component": "FormGrid",
      "x-validator": [],
      "x-component-props": {},
      "x-designable-id": "ztysj1mzc30",
      "x-index": 0,
      "properties": {
        "[startTime,endTime]": {
          "type": "string[]",
          "title": "时间范围",
          "x-decorator": "FormItem",
          "x-component": "DatePicker",
          "x-component-props": {
            "type": "daterange"
          },
          "x-index": 0
        },
        "orgId": {
          "title": "公司",
          "x-decorator": "FormItem",
          "x-component": "Select",
          "x-reactions": "{{useAsyncDataSource(getCompanyList, {init: true})}}",
          "x-component-props": {},
          "x-index": 1
        },
        "xo5r57zgh3u": {
          "type": "void",
          "x-component": "FormGrid",
          "x-designable-id": "xo5r57zgh3u",
          "x-index": 2
        }
      }
    }
  },
  "x-designable-id": "gjocuewcorj"
}
